{
	"defaultSshKey": "cloudymc_ansible_ssh_public_key_file",
	"timezone": "cloudymc_system_timezone",
	"minecraft.serverPort": "cloudymc_mc_port",
	"minecraft.additionalPorts": "cloudymc_mc_additional_ports",
	"minecraft.eulaAccepted": "cloudymc_mc_eula_accepted",
	"minecraft.onlineMode": "cloudymc_mc_online_mode",
	"minecraft.serverName": "cloudymc_mc_name",
	"minecraft.motd": "cloudymc_mc_motd",
	"minecraft.maxPlayers": "cloudymc_mc_max_players",
	"minecraft.gameMode": "cloudymc_mc_mode",
	"minecraft.version": "cloudymc_mc_version",
	"minecraft.difficulty": "cloudymc_mc_difficulty",
	"minecraft.hardcore": "cloudymc_mc_hardcore",
	"minecraft.pvp": "cloudymc_mc_pvp",
	"minecraft.allowFlight": "cloudymc_mc_allow_flight",
	"minecraft.levelType": "cloudymc_mc_level_type",
	"minecraft.seed": "cloudymc_mc_seed",
	"minecraft.viewDistance": "cloudymc_mc_view_distance",
	"minecraft.simulationDistance": "cloudymc_mc_simulation_distance",
	"minecraft.spawnProtection": "cloudymc_mc_spawn_protection",
	"minecraft.whitelist": "cloudymc_mc_whitelist",
	"minecraft.ops": "cloudymc_mc_ops",
	"minecraft.commands.onServerStartup": "cloudymc_mc_commands_startup",
	"minecraft.commands.onPlayerConnect": "cloudymc_mc_commands_connect",
	"minecraft.commands.onPlayerDisconnect": "cloudymc_mc_commands_disconnect"
}
